{"GlobalPropertiesHash":"buz+HaJMd/A2T2X/GiZ1CMlX6mAShFDhBDoiAWml9wM=","FingerprintPatternsHash":"gq3WsqcKBUGTSNle7RKKyXRIwh7M8ccEqOqYvIzoM04=","PropertyOverridesHash":"8ZRc1sGeVrPBx4lD717BgRaQekyh78QKV9SKsdt638U=","InputHashes":["UVuxowJOe9inCJ2ZB8eYaVKYX7AuG9qPfo5ZMBgH9nQ=","iCCzk9\u002BSHOxJaZksJ1cElHzoEAbJ1iVnhn3YQKzPAz8=","b9SWrxVZRW6ibMwN37G9ge7LTWgxKkCzII84UNRU798=","Zj00i/CVpd8xyTAjS98yxMCdbehfwY2hEJRJojOkCg0=","FqrH6EGyTJgQRzww0FoKB\u002BU6xoGrzm9rGIqEJV6sHXw=","F6F7jmD7nwZSVmJpPuEVI9laG\u002B3DhHRDBP0aRV9ATfE=","wYTWPDXIqjC4qETMqzxfS/SdC0UBSFaCIo2XkA9a\u002Bik=","\u002B9g8xQ1hEZeNkiHo9I6jlwnHMRWYaf1bWLlWEtizlDM=","Y/qpVWzQ3XQy6tuMSJOI4Mc80MnJ5Sesb6Vv6bLlcIE=","m68v1V9Z9i1r/3zJ8wkpArZsZmco8JJjimurjLp5oR8=","mxa453pFe7zKpkDTYdS/QObeU3M\u002B3gGfPyBtusnyQOw=","ESX2fSCE/Y\u002BFjWm6sb2Pa/\u002ByjnFxG\u002B4Q480DeVz2Utw=","x2QjGzU1eIyLFTrLZbUjazsEqjwcyjDAtmCpboSmQ2k=","Ht6NW0Ig55A6fys4BFc0\u002B8wi6MgPDqWeioQW1/ZF6wg=","NR39syIkHB8bgdk226sbVtHHjgoSjbDO2dFRUncgFUs=","Zn/KK3v1t2lBlPLXXn\u002BoYA50gMpY47Yvhh1CzK2dvUY=","jXkbGujvWQJz3k7Pg8\u002BqAUALMuqfcTbzzIUFTLGVM1A=","Mab6YhmIl44aLJbo2ECSavjTDMfizFT4Sjnpm3NgMNA=","1AURP\u002B\u002BqmaMP3gQXLdxNyFPEFn7XkgJTcwpLUYOA\u002BQw=","VQZN3eW3mImm3KgX2y8lqj8/nho6qxfcYTAgiH8Hi0A=","v/EgevIDU/IaTQ8D2ZFlWfNZ1lsJNiyATJBk3S23ogI=","P/U4tb7pT796Or84/6KmGnUnLt3\u002BzUNERfHDzh//c4Y=","F5AUvK\u002BGABGchHP\u002BKotEI/7KiiQ15\u002B4KN9FhddvpL34=","ABDz1MRDFh3FOV9X/bXtxiDSFmfdbob6yhHFOjK8KBQ=","TM8Lz\u002BHzCS1zt56jgD5Q48FNGrlaJBe4bk398/RJQrw=","vQtz\u002BJ4b02XkW1OG9sXJEFlOXvM6ZB1TVGBAmoOKjkc="],"CachedAssets":{"UVuxowJOe9inCJ2ZB8eYaVKYX7AuG9qPfo5ZMBgH9nQ=":{"Identity":"C:\\Users\\MYPC\\source\\repos\\BZDesktopApp\\wwwroot\\app.css","SourceId":"BZDesktopApp","SourceType":"Discovered","ContentRoot":"C:\\Users\\MYPC\\source\\repos\\BZDesktopApp\\wwwroot\\","BasePath":"_content/BZDesktopApp","RelativePath":"app#[.{fingerprint}]?.css","AssetKind":"All","AssetMode":"All","AssetRole":"Primary","AssetMergeBehavior":null,"AssetMergeSource":"","RelatedAsset":null,"AssetTraitName":null,"AssetTraitValue":null,"Fingerprint":"yo2yoohpll","Integrity":"3vXzOyEBhaGXFStasbQHrZWOSPNGHs6SNan3IP8/2XM=","CopyToOutputDirectory":"Never","CopyToPublishDirectory":"PreserveNewest","OriginalItemSpec":"wwwroot\\app.css","FileLength":55457,"LastWriteTime":"2025-11-04T10:08:23.5002031+00:00"},"iCCzk9\u002BSHOxJaZksJ1cElHzoEAbJ1iVnhn3YQKzPAz8=":{"Identity":"C:\\Users\\MYPC\\source\\repos\\BZDesktopApp\\wwwroot\\AppIcon.ico","SourceId":"BZDesktopApp","SourceType":"Discovered","ContentRoot":"C:\\Users\\MYPC\\source\\repos\\BZDesktopApp\\wwwroot\\","BasePath":"_content/BZDesktopApp","RelativePath":"AppIcon#[.{fingerprint}]?.ico","AssetKind":"All","AssetMode":"All","AssetRole":"Primary","AssetMergeBehavior":null,"AssetMergeSource":"","RelatedAsset":null,"AssetTraitName":null,"AssetTraitValue":null,"Fingerprint":"04lf0slsn0","Integrity":"YKcoVl2choGx7bzO9XsTikyl87fJcaMaTfpNPeOYU9Y=","CopyToOutputDirectory":"Never","CopyToPublishDirectory":"PreserveNewest","OriginalItemSpec":"wwwroot\\AppIcon.ico","FileLength":15406,"LastWriteTime":"2025-11-04T09:48:55.8165598+00:00"},"b9SWrxVZRW6ibMwN37G9ge7LTWgxKkCzII84UNRU798=":{"Identity":"C:\\Users\\MYPC\\source\\repos\\BZDesktopApp\\wwwroot\\css\\app.css","SourceId":"BZDesktopApp","SourceType":"Discovered","ContentRoot":"C:\\Users\\MYPC\\source\\repos\\BZDesktopApp\\wwwroot\\","BasePath":"_content/BZDesktopApp","RelativePath":"css/app#[.{fingerprint}]?.css","AssetKind":"All","AssetMode":"All","AssetRole":"Primary","AssetMergeBehavior":null,"AssetMergeSource":"","RelatedAsset":null,"AssetTraitName":null,"AssetTraitValue":null,"Fingerprint":"e5tk7yf482","Integrity":"bhCZyC/yM2\u002BDaFXr8z25\u002B5MeWfXWqMJNNA4ZLAXbjjU=","CopyToOutputDirectory":"Never","CopyToPublishDirectory":"PreserveNewest","OriginalItemSpec":"wwwroot\\css\\app.css","FileLength":3376,"LastWriteTime":"2025-11-04T09:48:55.8170744+00:00"},"Zj00i/CVpd8xyTAjS98yxMCdbehfwY2hEJRJojOkCg0=":{"Identity":"C:\\Users\\MYPC\\source\\repos\\BZDesktopApp\\wwwroot\\css\\bootstrap\\bootstrap.min.css","SourceId":"BZDesktopApp","SourceType":"Discovered","ContentRoot":"C:\\Users\\MYPC\\source\\repos\\BZDesktopApp\\wwwroot\\","BasePath":"_content/BZDesktopApp","RelativePath":"css/bootstrap/bootstrap.min#[.{fingerprint}]?.css","AssetKind":"All","AssetMode":"All","AssetRole":"Primary","AssetMergeBehavior":null,"AssetMergeSource":"","RelatedAsset":null,"AssetTraitName":null,"AssetTraitValue":null,"Fingerprint":"6gzpyzhau4","Integrity":"SiIVMGgRhdXjKSTIddX7mh9IbOXVcwQWc7/p4nS6D/0=","CopyToOutputDirectory":"Never","CopyToPublishDirectory":"PreserveNewest","OriginalItemSpec":"wwwroot\\css\\bootstrap\\bootstrap.min.css","FileLength":162726,"LastWriteTime":"2025-11-04T09:48:55.8170744+00:00"},"FqrH6EGyTJgQRzww0FoKB\u002BU6xoGrzm9rGIqEJV6sHXw=":{"Identity":"C:\\Users\\MYPC\\source\\repos\\BZDesktopApp\\wwwroot\\css\\bootstrap\\bootstrap.min.css.map","SourceId":"BZDesktopApp","SourceType":"Discovered","ContentRoot":"C:\\Users\\MYPC\\source\\repos\\BZDesktopApp\\wwwroot\\","BasePath":"_content/BZDesktopApp","RelativePath":"css/bootstrap/bootstrap.min.css#[.{fingerprint}]?.map","AssetKind":"All","AssetMode":"All","AssetRole":"Primary","AssetMergeBehavior":null,"AssetMergeSource":"","RelatedAsset":null,"AssetTraitName":null,"AssetTraitValue":null,"Fingerprint":"8inm30yfxf","Integrity":"gBwg2tmA0Ci2u54gMF1jNCVku6vznarkLS6D76htNNQ=","CopyToOutputDirectory":"Never","CopyToPublishDirectory":"PreserveNewest","OriginalItemSpec":"wwwroot\\css\\bootstrap\\bootstrap.min.css.map","FileLength":449111,"LastWriteTime":"2025-11-04T09:48:55.818593+00:00"},"F6F7jmD7nwZSVmJpPuEVI9laG\u002B3DhHRDBP0aRV9ATfE=":{"Identity":"C:\\Users\\MYPC\\source\\repos\\BZDesktopApp\\wwwroot\\images\\background\\login-bg.jpg","SourceId":"BZDesktopApp","SourceType":"Discovered","ContentRoot":"C:\\Users\\MYPC\\source\\repos\\BZDesktopApp\\wwwroot\\","BasePath":"_content/BZDesktopApp","RelativePath":"images/background/login-bg#[.{fingerprint}]?.jpg","AssetKind":"All","AssetMode":"All","AssetRole":"Primary","AssetMergeBehavior":null,"AssetMergeSource":"","RelatedAsset":null,"AssetTraitName":null,"AssetTraitValue":null,"Fingerprint":"s33ci665fl","Integrity":"SJvFqxbHf9r2W76bCncK37wD\u002B4/d6VHfkLeCEY8//vw=","CopyToOutputDirectory":"Never","CopyToPublishDirectory":"PreserveNewest","OriginalItemSpec":"wwwroot\\images\\background\\login-bg.jpg","FileLength":294868,"LastWriteTime":"2025-11-04T09:48:55.8201231+00:00"},"wYTWPDXIqjC4qETMqzxfS/SdC0UBSFaCIo2XkA9a\u002Bik=":{"Identity":"C:\\Users\\MYPC\\source\\repos\\BZDesktopApp\\wwwroot\\images\\logo\\bz-logo-green.png","SourceId":"BZDesktopApp","SourceType":"Discovered","ContentRoot":"C:\\Users\\MYPC\\source\\repos\\BZDesktopApp\\wwwroot\\","BasePath":"_content/BZDesktopApp","RelativePath":"images/logo/bz-logo-green#[.{fingerprint}]?.png","AssetKind":"All","AssetMode":"All","AssetRole":"Primary","AssetMergeBehavior":null,"AssetMergeSource":"","RelatedAsset":null,"AssetTraitName":null,"AssetTraitValue":null,"Fingerprint":"ivd1b6gxts","Integrity":"ggCBIj59IWG9J5yfaZwnpqxsIxx1DeOBY2HkzrWWQIw=","CopyToOutputDirectory":"Never","CopyToPublishDirectory":"PreserveNewest","OriginalItemSpec":"wwwroot\\images\\logo\\bz-logo-green.png","FileLength":7824,"LastWriteTime":"2025-11-04T09:48:55.8216414+00:00"},"\u002B9g8xQ1hEZeNkiHo9I6jlwnHMRWYaf1bWLlWEtizlDM=":{"Identity":"C:\\Users\\MYPC\\source\\repos\\BZDesktopApp\\wwwroot\\images\\logo\\bz-logo-white.png","SourceId":"BZDesktopApp","SourceType":"Discovered","ContentRoot":"C:\\Users\\MYPC\\source\\repos\\BZDesktopApp\\wwwroot\\","BasePath":"_content/BZDesktopApp","RelativePath":"images/logo/bz-logo-white#[.{fingerprint}]?.png","AssetKind":"All","AssetMode":"All","AssetRole":"Primary","AssetMergeBehavior":null,"AssetMergeSource":"","RelatedAsset":null,"AssetTraitName":null,"AssetTraitValue":null,"Fingerprint":"1ysxpdtvtf","Integrity":"N1IlvYcKBtOgYAeePAUoJnb38r6uq16LtFBBJ9EjETQ=","CopyToOutputDirectory":"Never","CopyToPublishDirectory":"PreserveNewest","OriginalItemSpec":"wwwroot\\images\\logo\\bz-logo-white.png","FileLength":8428,"LastWriteTime":"2025-11-04T09:48:55.8216414+00:00"},"Y/qpVWzQ3XQy6tuMSJOI4Mc80MnJ5Sesb6Vv6bLlcIE=":{"Identity":"C:\\Users\\MYPC\\source\\repos\\BZDesktopApp\\wwwroot\\index.html","SourceId":"BZDesktopApp","SourceType":"Discovered","ContentRoot":"C:\\Users\\MYPC\\source\\repos\\BZDesktopApp\\wwwroot\\","BasePath":"_content/BZDesktopApp","RelativePath":"index#[.{fingerprint}]?.html","AssetKind":"All","AssetMode":"All","AssetRole":"Primary","AssetMergeBehavior":null,"AssetMergeSource":"","RelatedAsset":null,"AssetTraitName":null,"AssetTraitValue":null,"Fingerprint":"nzw87rgyyq","Integrity":"A4z40wuZ1/EBIq3gQKpFYFXmSKO53GG2f8ShnqKhyN0=","CopyToOutputDirectory":"Never","CopyToPublishDirectory":"PreserveNewest","OriginalItemSpec":"wwwroot\\index.html","FileLength":1090,"LastWriteTime":"2025-11-04T09:48:55.8216414+00:00"},"m68v1V9Z9i1r/3zJ8wkpArZsZmco8JJjimurjLp5oR8=":{"Identity":"C:\\Users\\MYPC\\source\\repos\\BZDesktopApp\\wwwroot\\js\\flowbite-init.js","SourceId":"BZDesktopApp","SourceType":"Discovered","ContentRoot":"C:\\Users\\MYPC\\source\\repos\\BZDesktopApp\\wwwroot\\","BasePath":"_content/BZDesktopApp","RelativePath":"js/flowbite-init#[.{fingerprint}]?.js","AssetKind":"All","AssetMode":"All","AssetRole":"Primary","AssetMergeBehavior":null,"AssetMergeSource":"","RelatedAsset":null,"AssetTraitName":null,"AssetTraitValue":null,"Fingerprint":"p7z3q0kh2l","Integrity":"Ba/iXSD33KZSenpcfydqPCVdtVAeayddFPZeW8KWzas=","CopyToOutputDirectory":"Never","CopyToPublishDirectory":"PreserveNewest","OriginalItemSpec":"wwwroot\\js\\flowbite-init.js","FileLength":860,"LastWriteTime":"2025-11-04T09:48:55.8216414+00:00"},"mxa453pFe7zKpkDTYdS/QObeU3M\u002B3gGfPyBtusnyQOw=":{"Identity":"C:\\Users\\MYPC\\source\\repos\\BZDesktopApp\\wwwroot\\lib\\flowbite\\flowbite.min.js","SourceId":"BZDesktopApp","SourceType":"Discovered","ContentRoot":"C:\\Users\\MYPC\\source\\repos\\BZDesktopApp\\wwwroot\\","BasePath":"_content/BZDesktopApp","RelativePath":"lib/flowbite/flowbite.min#[.{fingerprint}]?.js","AssetKind":"All","AssetMode":"All","AssetRole":"Primary","AssetMergeBehavior":null,"AssetMergeSource":"","RelatedAsset":null,"AssetTraitName":null,"AssetTraitValue":null,"Fingerprint":"dzwycnnhus","Integrity":"hyyUWT0w6baDvSrh6TYtY0CWl/jRQt4qDJhWg64eEJg=","CopyToOutputDirectory":"Never","CopyToPublishDirectory":"PreserveNewest","OriginalItemSpec":"wwwroot\\lib\\flowbite\\flowbite.min.js","FileLength":135825,"LastWriteTime":"2025-11-04T09:48:52.6081409+00:00"}},"CachedCopyCandidates":{}}